{
  "crawled_instances": 19,
  "failed_instances": 6,
  "total_users": 17697,
  "total_online_users": 141,
  "instance_details": [
    {
      "domain": "lemmy.ml",
      "name": "Lemmy",
      "description": "A community of leftist privacy and FOSS enthusiasts, run by Lemmy’s developers",
      "version": "0.13.0",
      "icon": "https://lemmy.ml/pictrs/image/bhQ7ELa4oq.webp",
      "online_users": 91,
      "total_users": 12358,
      "users_active_halfyear": 1802,
      "users_active_month": 628,
      "open_registrations": true,
      "linked_instances_count": 27
    },
    {
      "domain": "lemmy.glasgow.social",
      "name": "lemmy.glasgow.social",
      "description": null,
      "version": "0.11.1",
      "icon": null,
      "online_users": 1,
      "total_users": 262,
      "users_active_halfyear": 181,
      "users_active_month": 120,
      "open_registrations": true,
      "linked_instances_count": 2
    },
    {
      "domain": "szmer.info",
      "name": "szmer",
      "description": "wykop wypok!",
      "version": "0.12.2",
      "icon": "https://szmer.info/pictrs/image/XcQWr0D2CU.png",
      "online_users": 29,
      "total_users": 637,
      "users_active_halfyear": 176,
      "users_active_month": 89,
      "open_registrations": true,
      "linked_instances_count": 5
    },
    {
      "domain": "lemmygrad.ml",
      "name": "Lemmygrad",
      "description": "A collection of leftist communities, for memes, learning, news, discussion, media, or anything you like.",
      "version": "0.13.0",
      "icon": "https://lemmygrad.ml/pictrs/image/gB8yP0oFF5.png",
      "online_users": 6,
      "total_users": 3186,
      "users_active_halfyear": 204,
      "users_active_month": 59,
      "open_registrations": true,
      "linked_instances_count": 10
    },
    {
      "domain": "lemmy.161.social",
      "name": "161.social",
      "description": null,
      "version": "0.12.2",
      "icon": "https://lemmy.161.social/pictrs/image/miFGgnYPfn.png",
      "online_users": 0,
      "total_users": 421,
      "users_active_halfyear": 108,
      "users_active_month": 38,
      "open_registrations": true,
      "linked_instances_count": 10
    },
    {
      "domain": "sopuli.xyz",
      "name": "Sopuli",
      "description": "A general purpose instance run by a Finn - everyone is welcome here!",
      "version": "0.13.0",
      "icon": "https://sopuli.xyz/pictrs/image/bFrkM7fL8u.png",
      "online_users": 1,
      "total_users": 165,
      "users_active_halfyear": 65,
      "users_active_month": 35,
      "open_registrations": true,
      "linked_instances_count": 27
    },
    {
      "domain": "baraza.africa",
      "name": "Baraza",
      "description": null,
      "version": "0.12.2",
      "icon": "https://baraza.africa/pictrs/image/qFpb6BEV2c.png",
      "online_users": 0,
      "total_users": 114,
      "users_active_halfyear": 57,
      "users_active_month": 26,
      "open_registrations": true,
      "linked_instances_count": 10
    },
    {
      "domain": "lemmy.eus",
      "name": "Lemmy.eus",
      "description": "Euskarazko lehen web-foro irekiak. Software librea, fedibertsoa, euskalmemeak, literatura... (Basque language)",
      "version": "0.12.1",
      "icon": "https://lemmy.eus/pictrs/image/thzN3hA4nW.png",
      "online_users": 6,
      "total_users": 211,
      "users_active_halfyear": 73,
      "users_active_month": 26,
      "open_registrations": true,
      "linked_instances_count": 5
    },
    {
      "domain": "feddit.de",
      "name": "Feddit",
      "description": "Deutschsprachige Lemmy Community",
      "version": "0.12.2",
      "icon": "https://feddit.de/pictrs/image/uI7Q7MuePp.png",
      "online_users": 0,
      "total_users": 41,
      "users_active_halfyear": 19,
      "users_active_month": 17,
      "open_registrations": true,
      "linked_instances_count": 9
    },
    {
      "domain": "lemmy.ca",
      "name": "Lemmy dot C.A.",
      "description": null,
      "version": "0.12.2",
      "icon": "https://lemmy.ca/pictrs/image/AX0BZv78yT.png",
      "online_users": 0,
      "total_users": 97,
      "users_active_halfyear": 38,
      "users_active_month": 16,
      "open_registrations": true,
      "linked_instances_count": 9
    },
    {
      "domain": "lemmy.schuerz.at",
      "name": "lemmy.schuerz.at",
      "description": null,
      "version": "0.12.2",
      "icon": null,
      "online_users": 0,
      "total_users": 36,
      "users_active_halfyear": 19,
      "users_active_month": 13,
      "open_registrations": false,
      "linked_instances_count": 13
    },
    {
      "domain": "lemmy.pt",
      "name": "Lemmy Portugal 🇵🇹",
      "description": "Uma instância pública de Lemmy dedicada a Portugal e à Língua Portuguesa.",
      "version": "0.12.2",
      "icon": "https://lemmy.pt/pictrs/image/fHkiLTfJNO.png",
      "online_users": 2,
      "total_users": 11,
      "users_active_halfyear": 7,
      "users_active_month": 7,
      "open_registrations": true,
      "linked_instances_count": 2
    },
    {
      "domain": "fapsi.be",
      "name": "Fapsi",
      "description": "This instance is for all the creative. No matter if you're a writer, author or illustrator.",
      "version": "0.12.2",
      "icon": "https://fapsi.be/pictrs/image/jUD7V242rr.png",
      "online_users": 1,
      "total_users": 46,
      "users_active_halfyear": 16,
      "users_active_month": 6,
      "open_registrations": true,
      "linked_instances_count": 7
    },
    {
      "domain": "stammtisch.hallertau.social",
      "name": "Stammtisch",
      "description": null,
      "version": "0.12.2",
      "icon": null,
      "online_users": 0,
      "total_users": 20,
      "users_active_halfyear": 9,
      "users_active_month": 5,
      "open_registrations": true,
      "linked_instances_count": 3
    },
    {
      "domain": "forum.nogafam.es",
      "name": "Foro de NoGAFAM",
      "description": null,
      "version": "0.10.3",
      "icon": "https://forum.nogafam.es/pictrs/image/GUUbHCRV1l.png",
      "online_users": 0,
      "total_users": 36,
      "users_active_halfyear": 19,
      "users_active_month": 4,
      "open_registrations": true,
      "linked_instances_count": 3
    },
    {
      "domain": "lemmy.cat",
      "name": "Lemmy CAT",
      "description": "Cultura catalana",
      "version": "0.12.1",
      "icon": "https://lemmy.cat/pictrs/image/MkQ0U2Qyck.png",
      "online_users": 0,
      "total_users": 36,
      "users_active_halfyear": 8,
      "users_active_month": 4,
      "open_registrations": false,
      "linked_instances_count": 3
    },
    {
      "domain": "lemmy.lohn.in",
      "name": "lohnmmy",
      "description": null,
      "version": "0.13.0",
      "icon": null,
      "online_users": 0,
      "total_users": 6,
      "users_active_halfyear": 4,
      "users_active_month": 4,
      "open_registrations": false,
      "linked_instances_count": 28
    },
    {
      "domain": "midwest.social",
      "name": "midwest.social",
      "description": "A lemmy server for, but not limited to, the Midwest USA",
      "version": "0.12.2",
      "icon": null,
      "online_users": 2,
      "total_users": 13,
      "users_active_halfyear": 5,
      "users_active_month": 4,
      "open_registrations": true,
      "linked_instances_count": 6
    },
    {
      "domain": "kallutatud.info",
      "name": "kallutatud.info",
      "description": "A general purpose instance from Estonia.",
      "version": "0.12.2",
      "icon": null,
      "online_users": 2,
      "total_users": 1,
      "users_active_halfyear": 1,
      "users_active_month": 1,
      "open_registrations": true,
      "linked_instances_count": 2
    }
  ]
}
